{
  "title": "[logstash-]YYYY.MM.DD",
  "timeFieldName": "@timestamp",
  "intervalName": "days",
  "customFormats": "{}",
  "fields": "[{\"type\":\"string\",\"indexed\":true,\"analyzed\":true,\"doc_values\":false,\"name\":\"request.headers.if-none-match\",\"count\":0,\"scripted\":false},{\"type\":\"string\",\"indexed\":false,\"analyzed\":false,\"name\":\"_index\",\"count\":0,\"scripted\":false},{\"type\":\"string\",\"indexed\":true,\"analyzed\":true,\"doc_values\":false,\"name\":\"pod\",\"count\":1,\"scripted\":false},{\"type\":\"number\",\"indexed\":true,\"analyzed\":false,\"doc_values\":false,\"name\":\"response.statusCode\",\"count\":0,\"scripted\":false},{\"type\":\"string\",\"indexed\":true,\"analyzed\":true,\"doc_values\":false,\"name\":\"log\",\"count\":6,\"scripted\":false},{\"type\":\"string\",\"indexed\":true,\"analyzed\":true,\"doc_values\":false,\"name\":\"node_env\",\"count\":0,\"scripted\":false},{\"type\":\"string\",\"indexed\":true,\"analyzed\":true,\"doc_values\":false,\"name\":\"request.headers.accept\",\"count\":0,\"scripted\":false},{\"type\":\"string\",\"indexed\":true,\"analyzed\":true,\"doc_values\":false,\"name\":\"request.headers.accept-language\",\"count\":0,\"scripted\":false},{\"type\":\"number\",\"indexed\":true,\"analyzed\":false,\"doc_values\":false,\"name\":\"response.contentLength\",\"count\":0,\"scripted\":false},{\"type\":\"string\",\"indexed\":true,\"analyzed\":true,\"doc_values\":false,\"name\":\"error\",\"count\":0,\"scripted\":false},{\"type\":\"string\",\"indexed\":true,\"analyzed\":true,\"doc_values\":false,\"name\":\"request.headers.host\",\"count\":0,\"scripted\":false},{\"type\":\"number\",\"indexed\":true,\"analyzed\":false,\"doc_values\":false,\"name\":\"request.remotePort\",\"count\":0,\"scripted\":false},{\"type\":\"string\",\"indexed\":true,\"analyzed\":true,\"doc_values\":false,\"name\":\"request.headers.content-type\",\"count\":0,\"scripted\":false},{\"type\":\"string\",\"indexed\":true,\"analyzed\":true,\"doc_values\":false,\"name\":\"stream\",\"count\":0,\"scripted\":false},{\"type\":\"string\",\"indexed\":true,\"analyzed\":true,\"doc_values\":false,\"name\":\"request.remoteAddress\",\"count\":0,\"scripted\":false},{\"type\":\"string\",\"indexed\":true,\"analyzed\":true,\"doc_values\":false,\"name\":\"request.headers.content-length\",\"count\":0,\"scripted\":false},{\"type\":\"string\",\"indexed\":true,\"analyzed\":true,\"doc_values\":false,\"name\":\"request.headers.accept-encoding\",\"count\":0,\"scripted\":false},{\"type\":\"string\",\"indexed\":true,\"analyzed\":true,\"doc_values\":false,\"name\":\"level\",\"count\":0,\"scripted\":false},{\"type\":\"string\",\"indexed\":true,\"analyzed\":true,\"doc_values\":false,\"name\":\"request.headers.referer\",\"count\":0,\"scripted\":false},{\"type\":\"string\",\"indexed\":true,\"analyzed\":false,\"name\":\"_type\",\"count\":0,\"scripted\":false},{\"type\":\"string\",\"indexed\":true,\"analyzed\":true,\"doc_values\":false,\"name\":\"request.method\",\"count\":0,\"scripted\":false},{\"type\":\"string\",\"indexed\":true,\"analyzed\":true,\"doc_values\":false,\"name\":\"request.url\",\"count\":0,\"scripted\":false},{\"type\":\"string\",\"indexed\":true,\"analyzed\":true,\"doc_values\":false,\"name\":\"message\",\"count\":0,\"scripted\":false},{\"type\":\"string\",\"indexed\":true,\"analyzed\":true,\"doc_values\":false,\"name\":\"request.headers.origin\",\"count\":0,\"scripted\":false},{\"type\":\"string\",\"indexed\":true,\"analyzed\":true,\"doc_values\":false,\"name\":\"request.headers.user-agent\",\"count\":0,\"scripted\":false},{\"type\":\"string\",\"indexed\":true,\"analyzed\":true,\"doc_values\":false,\"name\":\"pod_namespace\",\"count\":1,\"scripted\":false},{\"type\":\"date\",\"indexed\":true,\"analyzed\":false,\"doc_values\":false,\"name\":\"@timestamp\",\"count\":1,\"scripted\":false},{\"type\":\"string\",\"indexed\":true,\"analyzed\":true,\"doc_values\":false,\"name\":\"container_name\",\"count\":0,\"scripted\":false},{\"type\":\"string\",\"indexed\":true,\"analyzed\":true,\"doc_values\":false,\"name\":\"pod_container\",\"count\":1,\"scripted\":false},{\"type\":\"number\",\"indexed\":true,\"analyzed\":false,\"doc_values\":false,\"name\":\"response.responseTime\",\"count\":0,\"scripted\":false},{\"type\":\"string\",\"indexed\":false,\"analyzed\":false,\"name\":\"_source\",\"count\":0,\"scripted\":false},{\"type\":\"string\",\"indexed\":false,\"analyzed\":false,\"name\":\"_id\",\"count\":0,\"scripted\":false},{\"type\":\"string\",\"indexed\":true,\"analyzed\":true,\"doc_values\":false,\"name\":\"container_id\",\"count\":0,\"scripted\":false},{\"type\":\"string\",\"indexed\":true,\"analyzed\":true,\"doc_values\":false,\"name\":\"request.headers.if-modified-since\",\"count\":0,\"scripted\":false}]"
}